plain/observer/CHANGELOG.md
plain/observer/README.md
plain/observer/__init__.py
plain/observer/admin.py
plain/observer/cli.py
plain/observer/config.py
plain/observer/core.py
plain/observer/default_settings.py
plain/observer/logging.py
plain/observer/models.py
plain/observer/otel.py
plain/observer/toolbar.py
plain/observer/urls.py
plain/observer/views.py
plain/observer/assets/observer/observer.css
plain/observer/assets/observer/observer.js
plain/observer/migrations/0001_initial.py
plain/observer/migrations/0002_trace_share_created_at_trace_share_id_trace_summary_and_more.py
plain/observer/migrations/0003_span_plainobserv_span_id_e7ade3_idx.py
plain/observer/migrations/0004_trace_app_name_trace_app_version.py
plain/observer/migrations/0005_log_log_plainobserv_trace_i_fcfb7d_idx_and_more.py
plain/observer/migrations/0006_remove_log_logger.py
plain/observer/migrations/0007_remove_trace_plainobserv_share_i_754f3c_idx_and_more.py
plain/observer/migrations/__init__.py
plain/observer/skills/plain-optimize/SKILL.md
plain/observer/templates/observer/trace.html
plain/observer/templates/observer/trace_detail.html
plain/observer/templates/observer/traces.html
plain/observer/templates/observer/partials/log.html
plain/observer/templates/observer/partials/span.html
plain/observer/templates/toolbar/observer.html
plain/observer/templates/toolbar/observer_button.html
plain_observer-0.27.0.dist-info/METADATA
plain_observer-0.27.0.dist-info/WHEEL
plain_observer-0.27.0.dist-info/licenses/LICENSE
plain_observer-0.27.0.dist-info/RECORD
