Metadata-Version: 2.4
Name: plain.observer
Version: 0.27.0
Summary: On-page telemetry and observability tools for Plain.
Author-email: Dave Gaeddert <dave.gaeddert@dropseed.dev>
License-Expression: BSD-3-Clause
License-File: LICENSE
Requires-Python: >=3.13
Requires-Dist: opentelemetry-sdk>=1.34.1
Requires-Dist: plain-admin<1.0.0
Requires-Dist: plain<1.0.0
